sambal/__init__.py
sambal/sambal.py
sambal-0.1.0.dist-info/COPYING
sambal-0.1.0.dist-info/METADATA
sambal-0.1.0.dist-info/WHEEL
sambal-0.1.0.dist-info/top_level.txt
sambal-0.1.0.dist-info/RECORD
