Metadata-Version: 2.1
Name: sambal
Version: 0.1.0
Summary: Sample balls, spheres, spherical caps
Home-page: https://git.systemreboot.net/sambal
Author: Arun Isaac
Author-email: arunisaac@systemreboot.net
License: UNKNOWN
Platform: UNKNOWN
Classifier: Programming Language :: Python :: 3
Classifier: License :: OSI Approved :: GNU General Public License v3 or later (GPLv3+)
Classifier: Operating System :: OS Independent
